[
  {
    "_id": "6426e8ee73db4344dc73d813",
    "access_token": "",
    "APIKey": "",
    "CODE": "",
    "loginId": "admin",
    "loginPwd": "afdd0b4ad2ec172c586e2150770fbf9e",
    "name": "ikun",
    "refresh_token": "",
    "SecretKey": "",
    "tongJi": ""
  },
  {
    "_id": "60b9a35a63bdda282ff9ce6a",
    "access_token": null,
    "APIKey": null,
    "CODE": null,
    "loginId": "admin",
    "loginPwd": "e10adc3949ba59abbe56e057f20f883e",
    "name": "管理员",
    "refresh_token": null,
    "SecretKey": null,
    "tongJi": null
  }
]